[
  {
    "epoch": 6,
    "initiative": "0xba415afa8fcd65196764b5e08cb4dbf90bee33b4",
    "vetoLQTY": "0",
    "vetoOffset": "0",
    "voteLQTY": "3464693695469491722753",
    "voteOffset": "6063758183833826385230101427475"
  },
  {
    "epoch": 6,
    "initiative": "0xdc6f869d2d34e4aee3e89a51f2af6d54f0f7f690",
    "vetoLQTY": "0",
    "vetoOffset": "0",
    "voteLQTY": "384965966163276858084",
    "voteOffset": "673750909314869598359483544300"
  },
  {
    "epoch": 11,
    "initiative": "0xaeaa52a51e90cfe5d862568fdc99bc7510f53e04",
    "vetoLQTY": "0",
    "vetoOffset": "0",
    "voteLQTY": "3849659661632768580837",
    "voteOffset": "6737509093148695983589584971775"
  },
  {
    "epoch": 11,
    "initiative": "0xba415afa8fcd65196764b5e08cb4dbf90bee33b4",
    "vetoLQTY": "0",
    "vetoOffset": "0",
    "voteLQTY": "0",
    "voteOffset": "0"
  },
  {
    "epoch": 11,
    "initiative": "0xdc6f869d2d34e4aee3e89a51f2af6d54f0f7f690",
    "vetoLQTY": "0",
    "vetoOffset": "0",
    "voteLQTY": "0",
    "voteOffset": "0"
  }
]