[
  {
    "epoch": 2,
    "initiative": "0x0c76eae597afa2aa163a8c845f7e7e870256ac7e",
    "vetoLQTY": "0",
    "vetoOffset": "0",
    "voteLQTY": "50560589455339760096653",
    "voteOffset": "88362947037368686882738216435235"
  },
  {
    "epoch": 2,
    "initiative": "0xba415afa8fcd65196764b5e08cb4dbf90bee33b4",
    "vetoLQTY": "0",
    "vetoOffset": "0",
    "voteLQTY": "6741411927378634679554",
    "voteOffset": "11781726271649158251032228235230"
  },
  {
    "epoch": 2,
    "initiative": "0xdc6f869d2d34e4aee3e89a51f2af6d54f0f7f690",
    "vetoLQTY": "0",
    "vetoOffset": "0",
    "voteLQTY": "10112117891067952019331",
    "voteOffset": "17672589407473737376548342352845"
  },
  {
    "epoch": 4,
    "initiative": "0x0c76eae597afa2aa163a8c845f7e7e870256ac7e",
    "vetoLQTY": "0",
    "vetoOffset": "0",
    "voteLQTY": "0",
    "voteOffset": "0"
  },
  {
    "epoch": 4,
    "initiative": "0xba415afa8fcd65196764b5e08cb4dbf90bee33b4",
    "vetoLQTY": "0",
    "vetoOffset": "0",
    "voteLQTY": "71212438075602285214622",
    "voteOffset": "124464111644303309928760503242114"
  },
  {
    "epoch": 4,
    "initiative": "0xdc6f869d2d34e4aee3e89a51f2af6d54f0f7f690",
    "vetoLQTY": "0",
    "vetoOffset": "0",
    "voteLQTY": "3748023056610646590244",
    "voteOffset": "6550742718121226838357103802524"
  },
  {
    "epoch": 5,
    "initiative": "0xa58fbe38aab33b9fadef1b5aaff4d7bc27c43ad4",
    "vetoLQTY": "0",
    "vetoOffset": "0",
    "voteLQTY": "11244069169831939770731",
    "voteOffset": "19652228154363680515069563621441"
  },
  {
    "epoch": 5,
    "initiative": "0xba415afa8fcd65196764b5e08cb4dbf90bee33b4",
    "vetoLQTY": "0",
    "vetoOffset": "0",
    "voteLQTY": "59968368905770345443892",
    "voteOffset": "104811883489939629413692687406805"
  },
  {
    "epoch": 5,
    "initiative": "0xdc6f869d2d34e4aee3e89a51f2af6d54f0f7f690",
    "vetoLQTY": "0",
    "vetoOffset": "0",
    "voteLQTY": "3748023056610646590243",
    "voteOffset": "6550742718121226838355356016392"
  },
  {
    "epoch": 6,
    "initiative": "0x00000c771f6176268d5a9846e0956c3ef58597a1",
    "vetoLQTY": "0",
    "vetoOffset": "0",
    "voteLQTY": "11244069169831939770731",
    "voteOffset": "19652228154363680515069563621441"
  },
  {
    "epoch": 6,
    "initiative": "0xa58fbe38aab33b9fadef1b5aaff4d7bc27c43ad4",
    "vetoLQTY": "0",
    "vetoOffset": "0",
    "voteLQTY": "0",
    "voteOffset": "0"
  },
  {
    "epoch": 6,
    "initiative": "0xba415afa8fcd65196764b5e08cb4dbf90bee33b4",
    "vetoLQTY": "0",
    "vetoOffset": "0",
    "voteLQTY": "59968368905770345443892",
    "voteOffset": "104811883489939629413692687406805"
  },
  {
    "epoch": 6,
    "initiative": "0xdc6f869d2d34e4aee3e89a51f2af6d54f0f7f690",
    "vetoLQTY": "0",
    "vetoOffset": "0",
    "voteLQTY": "3748023056610646590243",
    "voteOffset": "6550742718121226838355356016392"
  },
  {
    "epoch": 7,
    "initiative": "0x00000c771f6176268d5a9846e0956c3ef58597a1",
    "vetoLQTY": "0",
    "vetoOffset": "0",
    "voteLQTY": "0",
    "voteOffset": "0"
  },
  {
    "epoch": 7,
    "initiative": "0xaeaa52a51e90cfe5d862568fdc99bc7510f53e04",
    "vetoLQTY": "0",
    "vetoOffset": "0",
    "voteLQTY": "74960461132212931804866",
    "voteOffset": "131014854362424536767117607044638"
  },
  {
    "epoch": 7,
    "initiative": "0xba415afa8fcd65196764b5e08cb4dbf90bee33b4",
    "vetoLQTY": "0",
    "vetoOffset": "0",
    "voteLQTY": "0",
    "voteOffset": "0"
  },
  {
    "epoch": 7,
    "initiative": "0xdc6f869d2d34e4aee3e89a51f2af6d54f0f7f690",
    "vetoLQTY": "0",
    "vetoOffset": "0",
    "voteLQTY": "0",
    "voteOffset": "0"
  }
]